goman_live_sdk/__init__.py
goman_live_sdk/prompt_sdk.py
goman_live_sdk-0.1.10.dist-info/LICENSE.md
goman_live_sdk-0.1.10.dist-info/METADATA
goman_live_sdk-0.1.10.dist-info/WHEEL
goman_live_sdk-0.1.10.dist-info/top_level.txt
goman_live_sdk-0.1.10.dist-info/RECORD
