Metadata-Version: 2.1
Name: goman-live-sdk
Version: 0.1.10
Summary: A Python SDK for fetching and managing prompts by goman.live
Home-page: https://github.com/bel-frontend/goman-live-sdk
Author: goman.live
Author-email: goman.live.service@gmail.com
License: UNKNOWN
Platform: UNKNOWN
Classifier: Programming Language :: Python :: 3
Classifier: License :: OSI Approved :: MIT License
Classifier: Operating System :: OS Independent
Requires-Python: >=3.6
License-File: LICENSE.md
Requires-Dist: requests (<3.0,>=2.20)
Requires-Dist: websocket-client (<2.0,>=1.7.0)
